sha256.sv
module sha256(
    input logic clock,
    input logic reset,
    input logic start,
    input logic [511:0] block,
    output logic [255:0] digest,
    output logic finish
);

    function automatic logic [31:0] rotate_right(input logic[31:0] in, input int positions);
        return (in >> positions) | (in << (32-positions));
    endfunction

    function automatic logic [31:0] s0(input logic[31:0] in);
        return (rotate_right(in, 7) ^ rotate_right(in,18) ^ (in >> 3));
    endfunction

    function automatic logic [31:0] s1(input logic [31:0] in);
        return (rotate_right(in, 17) ^ rotate_right(in, 19) ^ (in >> 10));
    endfunction

    function automatic logic [31:0] choose(input logic [31:0] select, input logic [31:0] x, input logic [31:0] y);
        return (x & select) ^ (y & ~select);
    endfunction

    function automatic logic [31:0] majority (input logic [31:0] j, input logic [31:0] k, input logic [31:0] l);
        return (j & k) ^ (j & l) ^ (k & l);
    endfunction

    function automatic logic [31:0] S0 (input logic [31:0] in);
        return rotate_right(in, 2) ^ rotate_right(in, 13) ^ rotate_right(in, 22);
    endfunction

    function automatic logic [31:0] S1 (input logic [31:0] in);
        return rotate_right(in, 6) ^ rotate_right(in, 11) ^ rotate_right(in ,25);
    endfunction

    // FIX: Use localparam (not reg + initial) so Quartus synthesizes K as a
    // compile-time constant, not a block RAM.  The reg+initial version was
    // for iverilog simulation compatibility only (see comment in original).
    // romstyle = "logic" forces a LUT-based combinational ROM, which gives
    // zero read latency and is required for the continuous 'assign' below.
    (* romstyle = "logic" *) localparam logic [31:0] K [0:63] = '{
        32'h428a2f98, 32'h71374491, 32'hb5c0fbcf, 32'he9b5dba5,
        32'h3956c25b, 32'h59f111f1, 32'h923f82a4, 32'hab1c5ed5,
        32'hd807aa98, 32'h12835b01, 32'h243185be, 32'h550c7dc3,
        32'h72be5d74, 32'h80deb1fe, 32'h9bdc06a7, 32'hc19bf174,
        32'he49b69c1, 32'hefbe4786, 32'h0fc19dc6, 32'h240ca1cc,
        32'h2de92c6f, 32'h4a7484aa, 32'h5cb0a9dc, 32'h76f988da,
        32'h983e5152, 32'ha831c66d, 32'hb00327c8, 32'hbf597fc7,
        32'hc6e00bf3, 32'hd5a79147, 32'h06ca6351, 32'h14292967,
        32'h27b70a85, 32'h2e1b2138, 32'h4d2c6dfc, 32'h53380d13,
        32'h650a7354, 32'h766a0abb, 32'h81c2c92e, 32'h92722c85,
        32'ha2bfe8a1, 32'ha81a664b, 32'hc24b8b70, 32'hc76c51a3,
        32'hd192e819, 32'hd6990624, 32'hf40e3585, 32'h106aa070,
        32'h19a4c116, 32'h1e376c08, 32'h2748774c, 32'h34b0bcb5,
        32'h391c0cb3, 32'h4ed8aa4a, 32'h5b9cca4f, 32'h682e6ff3,
        32'h748f82ee, 32'h78a5636f, 32'h84c87814, 32'h8cc70208,
        32'h90befffa, 32'ha4506ceb, 32'hbef9a3f7, 32'hc67178f2
    };

    logic [31:0] temp1;
    logic [31:0] temp2;
    (* ramstyle = "registers" *) logic [31:0] W [0:63];

    logic [31:0] a, b, c, d, e, f, g, h;
    logic [31:0] H0, H1, H2, H3, H4, H5, H6, H7;
    logic [31:0] w_update;
    logic [6:0] timer;

    // K is now localparam so K[timer[5:0]] resolves to a constant mux,
    // not a RAM read — no latency, no initialization ambiguity.
    assign temp1 = (timer < 64) ? (h + S1(e) + choose(e,f,g) + K[timer[5:0]] + w_update) : '0;
    assign temp2 = (timer < 64) ? (S0(a) + majority(a,b,c)) : '0;

    always_comb begin
        if (timer < 16) begin
            w_update = block[511 - timer * 32 -: 32];
        end else begin
            w_update = s1(W[timer-2]) + W[timer-7] + s0(W[timer-15]) + W[timer-16];
        end
    end

    always_ff @(posedge clock or negedge reset) begin
        if (!reset) begin

            timer <= 7'd65;
            finish <= 0;

            H0 <= 32'h6a09e667;
            H1 <= 32'hbb67ae85;
            H2 <= 32'h3c6ef372;
            H3 <= 32'ha54ff53a;
            H4 <= 32'h510e527f;
            H5 <= 32'h9b05688c;
            H6 <= 32'h1f83d9ab;
            H7 <= 32'h5be0cd19;

        end else if (start && timer > 63) begin

            finish <= 0;
            timer <= 7'd0;

            a <= 32'h6a09e667; b <= 32'hbb67ae85; c <= 32'h3c6ef372; d <= 32'ha54ff53a;
            e <= 32'h510e527f; f <= 32'h9b05688c; g <= 32'h1f83d9ab; h <= 32'h5be0cd19;

            H0 <= 32'h6a09e667; H1 <= 32'hbb67ae85; H2 <= 32'h3c6ef372; H3 <= 32'ha54ff53a;
            H4 <= 32'h510e527f; H5 <= 32'h9b05688c; H6 <= 32'h1f83d9ab; H7 <= 32'h5be0cd19;

        end else if (timer < 64) begin

            W[timer] <= w_update;

            h <= g;
            g <= f;
            f <= e;
            e <= d + temp1;
            d <= c;
            c <= b;
            b <= a;
            a <= temp1 + temp2;

            timer <= timer + 1;

        end else if (timer == 64) begin

            H0 <= H0 + a; H1 <= H1 + b; H2 <= H2 + c; H3 <= H3 + d;
            H4 <= H4 + e; H5 <= H5 + f; H6 <= H6 + g; H7 <= H7 + h;

            finish <= 1;
            timer <= 7'd65;

        end
    end

    assign digest = {H0, H1, H2, H3, H4, H5, H6, H7};

endmodule

tb_sha256.sv
`timescale 1ns/1ps

module tb_sha256;

    logic clk = 0;
    logic reset;
    logic start;
    logic [511:0] block;
    logic [255:0] digest;
    logic finish;
    logic [255:0] expected;

    always #5 clk = ~clk;

    sha256 dut (
        .clock(clk),
        .reset(reset),
        .start(start),
        .block(block),
        .digest(digest),
        .finish(finish)
    );

    integer file;
    integer scan_result;

    initial begin
        #1000000;
        $display("Error: Simulation timed out");
        $finish;
    end

    initial begin

        $dumpfile("wave.vcd");
        $dumpvars(0, tb_sha256);

        start = 0;
        block = 0;
        expected = 0;

        $display("Applying Reset...");
        reset = 0;
        #20;
        reset = 1; 
        #10;

        file = $fopen("examples.txt", "r");
        if (file == 0) $fatal(1, "Open examples.txt failed");

        while (!$feof(file)) begin

            scan_result = $fscanf(file, "%h %h\n", block, expected);
            
            if (scan_result == 2) begin
                
                @(negedge clk);
                reset = 0;
                
                @(negedge clk);
                reset = 1;

                @(negedge clk);
                start = 1;
                
                @(negedge clk);
                start = 0;

                wait(finish);
                
                @(posedge clk);

                if (digest !== expected) begin
                    $display("Error at time %0t", $time);
                    $display("Block:    %h", block);
                    $display("Got:      %h", digest);
                    $display("Expected: %h", expected);
                    $fatal(1, "Hash Mismatch!");
                end else begin
                    $display("Passed block %h...", block[511:480]);
                end
            end
        end

        $fclose(file);
        $display("Passed");
        $finish;
    end

endmodule

wave.vcd
$date
	Wed Apr 22 04:03:32 2026
$end
$version
	Icarus Verilog
$end
$timescale
	1ps
$end
$scope module tb_sha256 $end
$var wire 1 ! finish $end
$var wire 256 " digest [255:0] $end
$var reg 512 # block [511:0] $end
$var reg 1 $ clk $end
$var reg 256 % expected [255:0] $end
$var reg 1 & reset $end
$var reg 1 ' start $end
$var integer 32 ( file [31:0] $end
$var integer 32 ) scan_result [31:0] $end
$scope module dut $end
$var wire 512 * block [511:0] $end
$var wire 1 $ clock $end
$var wire 1 & reset $end
$var wire 1 ' start $end
$var wire 32 + temp2 [31:0] $end
$var wire 32 , temp1 [31:0] $end
$var wire 256 - digest [255:0] $end
$var reg 32 . H0 [31:0] $end
$var reg 32 / H1 [31:0] $end
$var reg 32 0 H2 [31:0] $end
$var reg 32 1 H3 [31:0] $end
$var reg 32 2 H4 [31:0] $end
$var reg 32 3 H5 [31:0] $end
$var reg 32 4 H6 [31:0] $end
$var reg 32 5 H7 [31:0] $end
$var reg 32 6 a [31:0] $end
$var reg 32 7 b [31:0] $end
$var reg 32 8 c [31:0] $end
$var reg 32 9 d [31:0] $end
$var reg 32 : e [31:0] $end
$var reg 32 ; f [31:0] $end
$var reg 1 ! finish $end
$var reg 32 < g [31:0] $end
$var reg 32 = h [31:0] $end
$var reg 7 > timer [6:0] $end
$var reg 32 ? w_update [31:0] $end
$scope function S0 $end
$upscope $end
$scope function S1 $end
$upscope $end
$scope function choose $end
$upscope $end
$scope function majority $end
$upscope $end
$scope function rotate_right $end
$upscope $end
$scope function s0 $end
$upscope $end
$scope function s1 $end
$upscope $end
$upscope $end
$upscope $end
$enddefinitions $end
$comment Show the parameter values. $end
$dumpall
$end
#0
$dumpvars
bx ?
b1000001 >
bx =
bx <
bx ;
bx :
bx 9
bx 8
bx 7
bx 6
b1011011111000001100110100011001 5
b11111100000111101100110101011 4
b10011011000001010110100010001100 3
b1010001000011100101001001111111 2
b10100101010011111111010100111010 1
b111100011011101111001101110010 0
b10111011011001111010111010000101 /
b1101010000010011110011001100111 .
b110101000001001111001100110011110111011011001111010111010000101001111000110111011110011011100101010010101001111111101010011101001010001000011100101001001111111100110110000010101101000100011000001111110000011110110011010101101011011111000001100110100011001 -
b0 ,
b0 +
b0 *
bx )
bx (
0'
0&
b0 %
0$
b0 #
b110101000001001111001100110011110111011011001111010111010000101001111000110111011110011011100101010010101001111111101010011101001010001000011100101001001111111100110110000010101101000100011000001111110000011110110011010101101011011111000001100110100011001 "
0!
$end
#5000
1$
#10000
0$
#15000
1$
#20000
0$
1&
#25000
1$
#30000
0&
0$
b10 )
b1101011000100010001010011001011100001001100011000110000101001011011011100011000101100001010100111110111101000010101010011000110000000101100011110100100101110011110101110100001001000111111011100011001010100000110111001011110000000000101101111111101110011100 %
b11110001000011110001100010110111010111111110110110011100111110000101111100000011011101001000100010011100101101100010011111010101110001000101010101101111100111100100000100011011010001100110011110111111110000011111000011110111001011100010010110101111011011011001100011110011000011000100111000111011111101000100010111100010010101010100000101000110110000011010011000101000101101101111110000111001100100001010000111111101101110001100000101110010101110001010000110111001100001001001111111010100011100100111011101001010 #
b11110001000011110001100010110111010111111110110110011100111110000101111100000011011101001000100010011100101101100010011111010101110001000101010101101111100111100100000100011011010001100110011110111111110000011111000011110111001011100010010110101111011011011001100011110011000011000100111000111011111101000100010111100010010101010100000101000110110000011010011000101000101101101111110000111001100100001010000111111101101110001100000101110010101110001010000110111001100001001001111111010100011100100111011101001010 *
b10000000000000000000000000000011 (
#35000
1$
#40000
1&
0$
#45000
1$
#50000
1'
0$
#55000
b11110001000011110001100010110111 ?
b11100100100001110000011000011111 ,
b1000100100001001101011100101 +
b1011011111000001100110100011001 =
b11111100000111101100110101011 <
b10011011000001010110100010001100 ;
b1010001000011100101001001111111 :
b10100101010011111111010100111010 9
b111100011011101111001101110010 8
b10111011011001111010111010000101 7
b1101010000010011110011001100111 6
b0 >
1$
#60000
0'
0$
#65000
b1011000111011100011100101001101 +
b11101010000110111101110000000111 ,
b1011111111011011001110011111000 ?
b1 >
b11101101000101111010000100000100 6
b1101010000010011110011001100111 7
b10111011011001111010111010000101 8
b111100011011101111001101110010 9
b10001001110101101111101101011001 :
b1010001000011100101001001111111 ;
b10011011000001010110100010001100 <
b11111100000111101100110101011 =
1$
#70000
0$
#75000
b11111101010000010111000101001101 +
b1010000001010011111101100111001 ,
b1011111000000110111010010001000 ?
b10 >
b1000011000010100001010101010100 6
b11101101000101111010000100000100 7
b1101010000010011110011001100111 8
b10111011011001111010111010000101 9
b100110100010101100111101111001 :
b10001001110101101111101101011001 ;
b1010001000011100101001001111111 <
b10011011000001010110100010001100 =
1$
#80000
0$
#85000
b10100111111001011100111001010011 +
b1100001011111010001110100001000 ,
b10011100101101100010011111010101 ?
b11 >
b1001101011010110110110010000110 6
b1000011000010100001010101010100 7
b11101101000101111010000100000100 8
b1101010000010011110011001100111 9
b1011100100011010100110111110 :
b100110100010101100111101111001 ;
b10001001110101101111101101011001 <
b1010001000011100101001001111111 =
1$
#90000
0$
#95000
b1011100100110000000101100111010 +
b11001000011000111101010110011000 ,
b11000100010101010110111110011110 ?
b100 >
b1001011000101110101101011011 6
b1001101011010110110110010000110 7
b1000011000010100001010101010100 8
b11101101000101111010000100000100 9
b11001011100001110000001101101111 :
b1011100100011010100110111110 ;
b100110100010101100111101111001 <
b10001001110101101111101101011001 =
1$
#100000
0$
#105000
b1101101100110001000000001001010 +
b1101010000100101011111111101101 ,
b1000001000110110100011001100111 ?
b101 >
b100100111110111110000011010010 6
b1001011000101110101101011011 7
b1001101011010110110110010000110 8
b1000011000010100001010101010100 9
b10110101011110110111011010011100 :
b11001011100001110000001101101111 ;
b1011100100011010100110111110 <
b100110100010101100111101111001 =
1$
#110000
0$
#115000
b1011111010000001001001001011100 +
b1100110000110011110001110100000 ,
b10111111110000011111000011110111 ?
b110 >
b11010111101010110100000000110111 6
b100100111110111110000011010010 7
b1001011000101110101101011011 8
b1001101011010110110110010000110 9
b10101101000111001101010101000001 :
b10110101011110110111011010011100 ;
b11001011100001110000001101101111 <
b1011100100011010100110111110 =
1$
#120000
0$
#125000
b10111101011000101010010110101111 +
b10100110111101111111111011111100 ,
b101110001001011010111101101101 ?
b111 >
b11000101010110100111010111111100 6
b11010111101010110100000000110111 7
b100100111110111110000011010010 8
b1001011000101110101101011011 9
b10110011100001010101000000100110 :
b10101101000111001101010101000001 ;
b10110101011110110111011010011100 <
b11001011100001110000001101101111 =
1$
#130000
0$
#135000
b1011100001110011000101100101101 +
b11100101111001100110110110100 ,
b10011000111100110000110001001110 ?
b1000 >
b1100100010110101010010010101011 6
b11000101010110100111010111111100 7
b11010111101010110100000000110111 8
b100100111110111110000011010010 9
b10110000010110101110101001010111 :
b10110011100001010101000000100110 ;
b10101101000111001101010101000001 <
b10110101011110110111011010011100 =
1$
#140000
0$
#145000
b10100100101100000100100101010010 +
b11000011010011000000011011011001 ,
b111011111101000100010111100010 ?
b1001 >
b1111000111101100101100011100001 6
b1100100010110101010010010101011 7
b11000101010110100111010111111100 8
b11010111101010110100000000110111 9
b1000001101110001010111010000110 :
b10110000010110101110101001010111 ;
b10110011100001010101000000100110 <
b10101101000111001101010101000001 =
1$
#150000
0$
#155000
b1110111000101101011100100010 +
b101001100010111101011010100101 ,
b1010101010000010100011011000001 ?
b1010 >
b1100111111111000101000000101011 6
b1111000111101100101100011100001 7
b1100100010110101010010010101011 8
b11000101010110100111010111111100 9
b10011010111101110100011100010000 :
b1000001101110001010111010000110 ;
b10110000010110101110101001010111 <
b10110011100001010101000000100110 =
1$
#160000
0$
#165000
b10010011100100111100110111001000 +
b10011000001011110001101000101000 ,
b10100110001010001011011011111100 ?
b1011 >
b111000011011101010110111000111 6
b1100111111111000101000000101011 7
b1111000111101100101100011100001 8
b1100100010110101010010010101011 9
b11101110111001100100110010100001 :
b10011010111101110100011100010000 ;
b1000001101110001010111010000110 <
b10110000010110101110101001010111 =
1$
#170000
0$
#175000
b1101010110111010000110100100111 +
b10101110010100001101100110101010 ,
b111001100100001010000111111101 ?
b1100 >
b101011110000101110011111110000 6
b111000011011101010110111000111 7
b1100111111111000101000000101011 8
b1111000111101100101100011100001 9
b11111100100010011011111011010011 :
b11101110111001100100110010100001 ;
b10011010111101110100011100010000 <
b1000001101110001010111010000110 =
1$
#180000
0$
#185000
b110001111101110010010000 +
b10011111100110011001110000101000 ,
b10111000110000010111001010111000 ?
b1101 >
b11001001011011110011011010001 6
b101011110000101110011111110000 7
b111000011011101010110111000111 8
b1100111111111000101000000101011 9
b100111010001110011001010001011 :
b11111100100010011011111011010011 ;
b11101110111001100100110010100001 <
b10011010111101110100011100010000 =
1$
#190000
0$
#195000
b10010001101000011010011010010100 +
b111000000100011001011011111001 ,
b10100001101110011000010010011111 ?
b1110 >
b10100000011000010111100010111000 6
b11001001011011110011011010001 7
b101011110000101110011111110000 8
b111000011011101010110111000111 9
b111100101011110110001010011 :
b100111010001110011001010001011 ;
b11111100100010011011111011010011 <
b11101110111001100100110010100001 =
1$
#200000
0$
#205000
b11011100000101100011001001110101 +
b1110100010011100000111011111111 ,
b11010100011100100111011101001010 ?
b1111 >
b11001001101100110011110110001101 6
b10100000011000010111100010111000 7
b11001001011011110011011010001 8
b101011110000101110011111110000 9
b1110000100000000100010011000000 :
b111100101011110110001010011 ;
b100111010001110011001010001011 <
b11111100100010011011111011010011 =
1$
#210000
0$
#215000
b1001111000111111011101111111010 +
b1011010111010110100011110110001 ,
b10111100011101000010100010000000 ?
b10000 >
b1010000011001000100000101110100 6
b11001001101100110011110110001101 7
b10100000011000010111100010111000 8
b11001001011011110011011010001 9
b10100000000100001111011011101111 :
b1110000100000000100010011000000 ;
b111100101011110110001010011 <
b100111010001110011001010001011 =
1$
#220000
0$
#225000
b10100011111101000011111111000111 +
b11011110000100101101000011011011 ,
b11110001001001001000111110011011 ?
b10001 >
b10101010000010110000001110101011 6
b1010000011001000100000101110100 7
b11001001101100110011110110001101 8
b10100000011000010111100010111000 9
b1110100000110010010111010000010 :
b10100000000100001111011011101111 ;
b1110000100000000100010011000000 <
b111100101011110110001010011 =
1$
#230000
0$
#235000
b10111011110111100101111110111010 +
b10000010000010111100011101011110 ,
b11001000000001100100111111011010 ?
b10010 >
b10000010000001110001000010100010 6
b10101010000010110000001110101011 7
b1010000011001000100000101110100 8
b11001001101100110011110110001101 9
b1111110011101000100100110010011 :
b1110100000110010010111010000010 ;
b10100000000100001111011011101111 <
b1110000100000000100010011000000 =
1$
#240000
0$
#245000
b1001001001100100000101000001010 +
b1011101010001110001000100110100 ,
b101011001011110100111110100000 ?
b10011 >
b111101111010100010011100011000 6
b10000010000001110001000010100010 7
b10101010000010110000001110101011 8
b1010000011001000100000101110100 9
b1001011101111110000010011101011 :
b1111110011101000100100110010011 ;
b1110100000110010010111010000010 <
b10100000000100001111011011101111 =
1$
#250000
0$
#255000
b111010011100101010001011011000 +
b10100010011111110101111000001110 ,
b10000010011100111010110011101100 ?
b10100 >
b10100110011110010001101100111110 6
b111101111010100010011100011000 7
b10000010000001110001000010100010 8
b10101010000010110000001110101011 9
b10101101101010110101001010101000 :
b1001011101111110000010011101011 ;
b1111110011101000100100110010011 <
b1110100000110010010111010000010 =
1$
#260000
0$
#265000
b110101000001000000000000011000 +
b100101100100010110111111001001 ,
b10110101101111011111100000110110 ?
b10101 >
b11011100111100100000000011100110 6
b10100110011110010001101100111110 7
b111101111010100010011100011000 8
b10000010000001110001000010100010 9
b1001100100010100110000110111001 :
b10101101101010110101001010101000 ;
b1001011101111110000010011101011 <
b1111110011101000100100110010011 =
1$
#270000
0$
#275000
b1011011000000010001011000011111 +
b10001000010010001000101001001 ,
b11101100010000110110101100010111 ?
b10110 >
b1011010100101010110111111100001 6
b11011100111100100000000011100110 7
b10100110011110010001101100111110 8
b111101111010100010011100011000 9
b10100111100110001000000001101011 :
b1001100100010100110000110111001 ;
b10101101101010110101001010101000 <
b1001011101111110000010011101011 =
1$
#280000
0$
#285000
b1100101011011100111000000011011 +
b10010110110100100001110001001101 ,
b1111011000001101101110010110001 ?
b10111 >
b1101100000010100010011101101000 6
b1011010100101010110111111100001 7
b11011100111100100000000011100110 8
b10100110011110010001101100111110 9
b1001110111100110011100001100001 :
b10100111100110001000000001101011 ;
b1001100100010100110000110111001 <
b10101101101010110101001010101000 =
1$
#290000
0$
#295000
b11011010011001101001001001010111 +
b100001000000010100100110111000 ,
b110101010110111010011000100110 ?
b11000 >
b11111100010000001000110001101000 6
b1101100000010100010011101101000 7
b1011010100101010110111111100001 8
b11011100111100100000000011100110 9
b111101010010110011011110001011 :
b1001110111100110011100001100001 ;
b10100111100110001000000001101011 <
b1001100100010100110000110111001 =
1$
#300000
0$
#305000
b1111110000110001010000000111000 +
b11110100000110001001111000010101 ,
b10010011011111011110100000010101 ?
b11001 >
b11111011011001111101110000001111 6
b11111100010000001000110001101000 7
b1101100000010100010011101101000 8
b1011010100101010110111111100001 9
b11111101111100110100101010011110 :
b111101010010110011011110001011 ;
b1001110111100110011100001100001 <
b10100111100110001000000001101011 =
1$
#310000
0$
#315000
b1100100100000001000100000011111 +
b10010110010100001100000100100001 ,
b11101000100000011000111110001000 ?
b11010 >
b1110010001100010011111001001101 6
b11111011011001111101110000001111 7
b11111100010000001000110001101000 8
b1101100000010100010011101101000 9
b1001110101011100000110111110110 :
b11111101111100110100101010011110 ;
b111101010010110011011110001011 <
b1001110111100110011100001100001 =
1$
#320000
0$
#325000
b101100000001111110001101111110 +
b1011011101101001010101000010001 ,
b1000111000001111000001110101011 ?
b11011 >
b11111010110100010100100101000000 6
b1110010001100010011111001001101 7
b11111011011001111101110000001111 8
b11111100010000001000110001101000 9
b10010110101110100010001001 :
b1001110101011100000110111110110 ;
b11111101111100110100101010011110 <
b111101010010110011011110001011 =
1$
#330000
0$
#335000
b1110010010101100010110111100110 +
b11000000010000001111110011011100 ,
b100000001001010110010111101000 ?
b11100 >
b10000111101111001000110110001111 6
b11111010110100010100100101000000 7
b1110010001100010011111001001101 8
b11111011011001111101110000001111 9
b1010111111101010011011001111001 :
b10010110101110100010001001 ;
b1001110101011100000110111110110 <
b11111101111100110100101010011110 =
1$
#340000
0$
#345000
b111000101101000110000010000101 +
b11000001010001110000011110010001 ,
b100001000010011001010001000110 ?
b11101 >
b110010100101110010101011000010 6
b10000111101111001000110110001111 7
b11111010110100010100100101000000 8
b1110010001100010011111001001101 9
b10111011101010001101100011101011 :
b1010111111101010011011001111001 ;
b10010110101110100010001001 <
b1001110101011100000110111110110 =
1$
#350000
0$
#355000
b11000111001010000111011010111111 +
b1001101111100011011110110000101 ,
b1001101111101011001110110111010 ?
b11110 >
b11111001111110110110100000010110 6
b110010100101110010101011000010 7
b10000111101111001000110110001111 8
b11111010110100010100100101000000 9
b110011011110000100010111011110 :
b10111011101010001101100011101011 ;
b1010111111101010011011001111001 <
b10010110101110100010001001 =
1$
#360000
0$
#365000
b1010100100101110111011010 +
b11101010110110001010101000111001 ,
b11111010001111111011010001100 ?
b11111 >
b10101000110100011010001000100 6
b11111001111110110110100000010110 7
b110010100101110010101011000010 8
b10000111101111001000110110001111 9
b1001000110000110000011011000101 :
b110011011110000100010111011110 ;
b10111011101010001101100011101011 <
b1010111111101010011011001111001 =
1$
#370000
0$
#375000
b10100111100010001010100000010 +
b10001111001101000101001111100011 ,
b11010111100010110100011101011101 ?
b100000 >
b11101100001010110000100000010011 6
b10101000110100011010001000100 7
b11111001111110110110100000010110 8
b110010100101110010101011000010 9
b1110010100101010011011111001000 :
b1001000110000110000011011000101 ;
b110011011110000100010111011110 <
b10111011101010001101100011101011 =
1$
#380000
0$
#385000
b1011111101100110001010111000111 +
b1101110101100011101100010001001 ,
b11110100111001111010000111110 ?
b100001 >
b10100100001001010110100011100101 6
b11101100001010110000100000010011 7
b10101000110100011010001000100 8
b11111001111110110110100000010110 9
b11000001110010110111111010100101 :
b1110010100101010011011111001000 ;
b1001000110000110000011011000101 <
b110011011110000100010111011110 =
1$
#390000
0$
#395000
b10111110110010110111001111011011 +
b10010010110100110010000010101110 ,
b1110001010110100100010100001010 ?
b100010 >
b11001110011001001110111001010000 6
b10100100001001010110100011100101 7
b11101100001010110000100000010011 8
b10101000110100011010001000100 9
b1101000101011010100000010011111 :
b11000001110010110111111010100101 ;
b1110010100101010011011111001000 <
b1001000110000110000011011000101 =
1$
#400000
0$
#405000
b1001110101000111111100101010001 +
b11011010000111011010010011100 ,
b1010010011001011101001110000000 ?
b100011 >
b1010001100111101001010010001001 6
b11001110011001001110111001010000 7
b10100100001001010110100011100101 8
b11101100001010110000100000010011 9
b10100111111011010101010011110010 :
b1101000101011010100000010011111 ;
b11000001110010110111111010100101 <
b1110010100101010011011111001000 =
1$
#410000
0$
#415000
b11110101100010111011111010101010 +
b1001000111011010001001000110011 ,
b10011100001101100101011100010 ?
b100100 >
b1101001111001111010110111101101 6
b1010001100111101001010010001001 7
b11001110011001001110111001010000 8
b10100100001001010110100011100101 9
b111011011101011110010101111 :
b10100111111011010101010011110010 ;
b1101000101011010100000010011111 <
b11000001110010110111111010100101 =
1$
#420000
0$
#425000
b10100100001100110100011111010101 +
b10110000100010000101000010110111 ,
b111111111011010110000010011110 ?
b100101 >
b111110011110001101000011011101 6
b1101001111001111010110111101101 7
b1010001100111101001010010001001 8
b11001110011001001110111001010000 9
b11101101000100100111101100011000 :
b111011011101011110010101111 ;
b10100111111011010101010011110010 <
b1101000101011010100000010011111 =
1$
#430000
0$
#435000
b10111100001010100000101101111010 +
b11000100101011100101100100111110 ,
b10100010011011111001010010010010 ?
b100110 >
b1010100101110111001100010001100 6
b111110011110001101000011011101 7
b1101001111001111010110111101101 8
b1010001100111101001010010001001 9
b1111110111011010011111100000111 :
b11101101000100100111101100011000 ;
b111011011101011110010101111 <
b10100111111011010101010011110010 =
1$
#440000
0$
#445000
b1111001010110011100111010001010 +
b101110001110011101100000110011 ,
b10010001011011001011000111111 ?
b100111 >
b10000000110110000110010010111000 6
b1010100101110111001100010001100 7
b111110011110001101000011011101 8
b1101001111001111010110111101101 9
b10110010011001110110111000111 :
b1111110111011010011111100000111 ;
b11101101000100100111101100011000 <
b111011011101011110010101111 =
1$
#450000
0$
#455000
b10010111001011101100100001101000 +
b101101100010000000111000110100 ,
b11010000001110000101101100010000 ?
b101000 >
b10100111100100111010011010111101 6
b10000000110110000110010010111000 7
b1010100101110111001100010001100 8
b111110011110001101000011011101 9
b10011000001000011000011000100000 :
b10110010011001110110111000111 ;
b1111110111011010011111100000111 <
b11101101000100100111101100011000 =
1$
#460000
0$
#465000
b11100011001001001100100110111111 +
b11010111000111100110111000001100 ,
b11101101110110000001011000100011 ?
b101001 >
b11000100101101101101011010011100 6
b10100111100100111010011010111101 7
b10000000110110000110010010111000 8
b1010100101110111001100010001100 9
b1101100000000001101111100010001 :
b10011000001000011000011000100000 ;
b10110010011001110110111000111 <
b1111110111011010011111100000111 =
1$
#470000
0$
#475000
b10101001011110011110011111 +
b1111101011010110110001111110 ,
b100000010010100000110111001000 ?
b101010 >
b10111010010000110011011111001011 6
b11000100101101101101011010011100 7
b10100111100100111010011010111101 8
b10000000110110000110010010111000 9
b101011110110100000011010011000 :
b1101100000000001101111100010001 ;
b10011000001000011000011000100000 <
b10110010011001110110111000111 =
1$
#480000
0$
#485000
b111011011111111000101001110001 +
b1111100010000101011110011101000 ,
b11110001101111000011101001011110 ?
b101011 >
b10010010100110101010000011101 6
b10111010010000110011011111001011 7
b11000100101101101101011010011100 8
b10100111100100111010011010111101 9
b10010000100001011101000100110110 :
b101011110110100000011010011000 ;
b1101100000000001101111100010001 <
b10011000001000011000011000100000 =
1$
#490000
0$
#495000
b10000011000111010000001110100 +
b11100110000101010111010101010000 ,
b10010100110110100111011100010111 ?
b101100 >
b10110111110000100100011101011001 6
b10010010100110101010000011101 7
b10111010010000110011011111001011 8
b11000100101101101101011010011100 9
b100011110101100110001110100101 :
b10010000100001011101000100110110 ;
b101011110110100000011010011000 <
b1101100000000001101111100010001 =
1$
#500000
0$
#505000
b101110010000100011101010111101 +
b1010110011100100011111000010101 ,
b1111000000111011011111010110000 ?
b101101 >
b11110110011110010001010111000100 6
b10110111110000100100011101011001 7
b10010010100110101010000011101 8
b10111010010000110011011111001011 9
b10101010110011000100101111101100 :
b100011110101100110001110100101 ;
b10010000100001011101000100110110 <
b101011110110100000011010011000 =
1$
#510000
0$
#515000
b1101101010010101100011101010101 +
b11001011001110010011011101100010 ,
b10111011111001001011100101010001 ?
b101110 >
b10000100101101000111100011010010 6
b11110110011110010001010111000100 7
b10110111110000100100011101011001 8
b10010010100110101010000011101 9
b10000101101010111010111100000 :
b10101010110011000100101111101100 ;
b100011110101100110001110100101 <
b10010000100001011101000100110110 =
1$
#520000
0$
#525000
b11101001000101010110010000100110 +
b10000110011001110001001111001100 ,
b11001000100110011001000110000101 ?
b101111 >
b111000100000111111111010110111 6
b10000100101101000111100011010010 7
b11110110011110010001010111000100 8
b10110111110000100100011101011001 9
b11011101100011001000101101111111 :
b10000101101010111010111100000 ;
b10101010110011000100101111101100 <
b100011110101100110001110100101 =
1$
#530000
0$
#535000
b10010010000010111010010100 +
b10011001111100001100000110100111 ,
b11010011111100001001000111101000 ?
b110000 >
b1101111011111000111011111110010 6
b111000100000111111111010110111 7
b10000100101101000111100011010010 8
b11110110011110010001010111000100 9
b111110001010010101101100100101 :
b11011101100011001000101101111111 ;
b10000101101010111010111100000 <
b10101010110011000100101111101100 =
1$
#540000
0$
#545000
b11000001010010110010101001101100 +
b11001001101001010011101010001010 ,
b11000101001100101101110110111110 ?
b110001 >
b10011100001110001111000000111011 6
b1101111011111000111011111110010 7
b111000100000111111111010110111 8
b10000100101101000111100011010010 9
b10010000011010011101011101101011 :
b111110001010010101101100100101 ;
b11011101100011001000101101111111 <
b10000101101010111010111100000 =
1$
#550000
0$
#555000
b11010011000101000000100110000111 +
b10100111110001000101011001101000 ,
b111100000111000111010001011000 ?
b110010 >
b10001010111100000110010011110110 6
b10011100001110001111000000111011 7
b1101111011111000111011111110010 8
b111000100000111111111010110111 9
b1001110010110011011001101011100 :
b10010000011010011101011101101011 ;
b111110001010010101101100100101 <
b11011101100011001000101101111111 =
1$
#560000
0$
#565000
b11011011101010101111000111010001 +
b1001101001001001110010001001011 ,
b10010001100010011001000101000111 ?
b110011 >
b1111010110110000101111111101111 6
b10001010111100000110010011110110 7
b10011100001110001111000000111011 8
b1101111011111000111011111110010 9
b11100000010010000101010100011111 :
b1001110010110011011001101011100 ;
b10010000011010011101011101101011 <
b111110001010010101101100100101 =
1$
#570000
0$
#575000
b10110000011000110001101001011000 +
b1110001101111001000110001001011 ,
b10100011111100101010000101001011 ?
b110100 >
b101000110011111101011000011100 6
b1111010110110000101111111101111 7
b10001010111100000110010011110110 8
b10011100001110001111000000111011 9
b10111100101000010101110000111101 :
b11100000010010000101010100011111 ;
b1001110010110011011001101011100 <
b10010000011010011101011101101011 =
1$
#580000
0$
